MANIFEST.in
README.md
setup.py
bitly/__init__.py
bitly/bitly.py
hpx_bitly.egg-info/PKG-INFO
hpx_bitly.egg-info/SOURCES.txt
hpx_bitly.egg-info/dependency_links.txt
hpx_bitly.egg-info/top_level.txt
hpx_bitly.egg-info/zip-safe
test/test_bitly_api.py