Metadata-Version: 1.0
Name: hpx-bitly
Version: 0.1
Summary: An API for bit.ly. Forked from bitly-api-python which is not updating the project
Home-page: UNKNOWN
Author: UNKNOWN
Author-email: UNKNOWN
License: UNKNOWN
Platform: UNKNOWN
